{
  "$schema": "https://developer.microsoft.com/json-schemas/fabric/item/report/definition/visualContainer/2.10.0/schema.json",
  "name": "beb4405e27be56089d4e",
  "position": {
    "x": 8,
    "y": 116,
    "z": 1000,
    "height": 280,
    "width": 420
  },
  "visual": {
    "visualType": "pivotTable",
    "query": {
      "queryState": {
        "Columns": {
          "projections": [
            {
              "field": {
                "Column": {
                  "Expression": {
                    "SourceRef": {
                      "Entity": "Risk"
                    }
                  },
                  "Property": "Impact"
                }
              },
              "queryRef": "Risk.Impact",
              "active": true
            }
          ]
        },
        "Rows": {
          "projections": [
            {
              "field": {
                "Column": {
                  "Expression": {
                    "SourceRef": {
                      "Entity": "Risk"
                    }
                  },
                  "Property": "Likelihood"
                }
              },
              "queryRef": "Risk.Likelihood",
              "active": true
            }
          ]
        },
        "Values": {
          "projections": [
            {
              "field": {
                "Measure": {
                  "Expression": {
                    "SourceRef": {
                      "Entity": "_Measures"
                    }
                  },
                  "Property": "Risks"
                }
              },
              "queryRef": "_Measures.Risks"
            }
          ]
        }
      }
    },
    "visualContainerObjects": {
      "title": [
        {
          "properties": {
            "show": {
              "expr": {
                "Literal": {
                  "Value": "true"
                }
              }
            },
            "text": {
              "expr": {
                "Literal": {
                  "Value": "'5x5 heat map - likelihood x impact'"
                }
              }
            }
          }
        }
      ]
    },
    "drillFilterOtherVisuals": true
  }
}